Workbook

Sheet Map
R11: Note - Please interact with the map. On clicking the different suburbs, you get redirected to the individual data table and visualisation for the Suburb. There is a separate button for the Comparitive Data (KPI) to view a comparison between all 6 councils.

Sheet Consolidated data
E2: Hornsby Shire Council | L2: North Sydney Council | P2: Woollahra Municipal Council | T2: City of Sydney | X2: City of Parramatta Council | AB2: The Hills Shire Council
B3: Accounts | C3: Account Category | E3: Budget FY 25 | F3: Actual FY 25 | G3: Actual FY 24 | I3: vs Budget | J3: YoY | L3: Budget FY 25 | M3: Actual FY 25 | N3: Actual FY 24 | P3: Budget FY 25 | Q3: Actual FY 25 | R3: Actual FY 24 | T3: Budget FY 25 | U3: Actual FY 25 | V3: Actual FY 24 | X3: Budget FY 25 | Y3: Actual FY 25 | Z3: Actual FY 24 | AB3: Budget FY 25 | AC3: Actual FY 25 | AD3: Actual FY 24
B4: Rates and annual charges | C4: Direct Income | E4: 125129 | F4: 126012 | G4: 116643 | I4: =F4-E4 -> 883 | J4: =F4/G4-1 -> 0.080322008 | L4: 79066 | M4: 79820 | N4: 75559 | P4: 70681 | Q4: 70552 | R4: 66136 | T4: 419230 | U4: 420955 | V4: 397592 | X4: 229252 | Y4: 231565 | Z4: 221620 | AB4: 142994 | AC4: 144008 | AD4: 128728
B5: User charges and fees | C5: Direct Income | E5: 14958 | F5: 16427 | G5: 14762 | I5: =F5-E5 -> 1469 | J5: =F5/G5-1 -> 0.11278959 | L5: 36774 | M5: 30734 | N5: 32134 | P5: 14655 | Q5: 16689 | R5: 15565 | T5: 149206 | U5: 162346 | V5: 163152 | X5: 49973 | Y5: 46819 | Z5: 41788 | AB5: 29911 | AC5: 35509 | AD5: 31193
B6: Other revenues | C6: Other Income | E6: 3963 | F6: 4636 | G6: 4179 | I6: =F6-E6 -> 673 | J6: =F6/G6-1 -> 0.10935631 | L6: 10216 | M6: 13967 | N6: 10239 | P6: 16941 | Q6: 15347 | R6: 16230 | T6: 42362 | U6: 50103 | V6: 41915 | X6: 18880 | Y6: 18382 | Z6: 12358 | AB6: 6933 | AC6: 9660 | AD6: 9312
B7: Grants and contributions provided for operating purposes | C7: Direct Income | E7: 9174 | F7: 13562 | G7: 10642 | I7: =F7-E7 -> 4388 | J7: =F7/G7-1 -> 0.27438451 | L7: 4666 | M7: 4869 | N7: 5453 | P7: 5014 | Q7: 4615 | R7: 5676 | T7: 17477 | U7: 15652 | V7: 16508 | X7: 23721 | Y7: 17849 | Z7: 16057 | AB7: 19810 | AC7: 18992 | AD7: 23113
B8: Grants and contributions provided for capital purposes | C8: Direct Income | E8: 9940 | F8: 41945 | G8: -22203 | I8: =F8-E8 -> 32005 | J8: =F8/G8-1 -> -2.8891591 | L8: 3058 | M8: 13909 | N8: 16690 | P8: 2897 | Q8: 8612 | R8: 16212 | T8: 95048 | U8: 111331 | V8: 117839 | X8: 75732 | Y8: 69198 | Z8: 57452 | AB8: 102404 | AC8: 167184 | AD8: 154622
B9: Interest and investment income | C9: Other Income | E9: 10271 | F9: 12548 | G9: 12970 | I9: =F9-E9 -> 2277 | J9: =F9/G9-1 -> -0.032536623 | L9: 2665 | M9: 5759 | N9: 5612 | P9: 3223 | Q9: 6103 | R9: 5626 | T9: 34285 | U9: 39676 | V9: 39591 | X9: 23690 | Y9: 28486 | Z9: 30898 | AB9: 12978 | AC9: 30305 | AD9: 25956
B10: Other income | C10: Other Income | E10: 4050 | F10: 9991 | G10: 5759 | I10: =F10-E10 -> 5941 | J10: =F10/G10-1 -> 0.7348498 | L10: 5887 | M10: 5522 | N10: 5970 | P10: 17920 | Q10: 17655 | R10: 17608 | T10: 88075 | U10: 109685 | V10: 100738 | X10: 600 | Y10: 26905 | Z10: 91653 | AB10: 8427 | AC10: 8691 | AD10: 8152 | AG10: Total Rev
B11: Fair Value increment / (Decrement) on Investment Properties | C11: Other Income | E11: 0 | F11: 0 | G11: 0 | I11: =F11-E11 -> 0 | J11: =F11/G11-1 -> #DIV/0! | L11: 0 | M11: 0 | N11: 0 | P11: 1200 | Q11: 19 | R11: -6683 | T11: 0 | U11: 0 | V11: 0
B12: Net Gain from disposal of Assets | C12: Other Income | J12: =F12/G12-1 -> #DIV/0! | T12: 0 | U12: 0 | V12: 17242 | AB12: 1262 | AC12: 3102 | AD12: 2407 | AG12: Profit
B13: Total income from continuing operations | C13: Total Income | E13: =SUM(E4:E12) -> 177485 | F13: =SUM(F4:F12) -> 225121 | G13: =SUM(G4:G12) -> 142752 | I13: =SUM(I4:I12) -> 47636 | J13: =F13/G13-1 -> 0.57700768 | L13: =SUM(L4:L12) -> 142332 | M13: =SUM(M4:M12) -> 154580 | N13: =SUM(N4:N12) -> 151657 | P13: =SUM(P4:P12) -> 132531 | Q13: =SUM(Q4:Q12) -> 139592 | R13: =SUM(R4:R12) -> 136370 | T13: =SUM(T4:T12) -> 845683 | U13: =SUM(U4:U12) -> 909748 | V13: =SUM(V4:V12) -> 894577 | X13: =SUM(X4:X12) -> 421848 | Y13: =SUM(Y4:Y12) -> 439204 | Z13: =SUM(Z4:Z12) -> 471826 | AB13: =SUM(AB4:AB12) -> 324719 | AC13: =SUM(AC4:AC12) -> 417451 | AD13: =SUM(AD4:AD12) -> 383483
B14: Employee benefits and on-costs | C14: Direct Expenses | E14: 58497 | F14: 58441 | G14: 54031 | I14: =F14-E14 -> -56 | J14: =F14/G14-1 -> 0.081619811 | L14: 55651 | M14: 48080 | N14: 49118 | P14: 53223 | Q14: 52968 | R14: 47706 | T14: 289337 | U14: 306623 | V14: 276897 | X14: 145934 | Y14: 164786 | Z14: 159530 | AB14: 83698 | AC14: 81713 | AD14: 73247
B15: Materials and services | C15: Direct Expenses | E15: 71796 | F15: 72268 | G15: 82222 | I15: =F15-E15 -> 472 | J15: =F15/G15-1 -> -0.12106249 | L15: 53337 | M15: 52555 | N15: 51176 | P15: 48496 | Q15: 51840 | R15: 50408 | T15: 244959 | U15: 286173 | V15: 299048 | X15: 72736 | Y15: 135446 | Z15: 129925 | AB15: 88447 | AC15: 89550 | AD15: 79966
B16: Borrowing costs | C16: Other Expenses | E16: 10 | F16: 23 | G16: 16 | I16: =F16-E16 -> 13 | J16: =F16/G16-1 -> 0.4375 | L16: 2382 | M16: 2365 | N16: 1497 | P16: 3014 | Q16: 1745 | R16: 1806 | T16: 0 | U16: 211 | V16: 216 | X16: 98 | Y16: 47 | Z16: 135 | AB16: 0 | AC16: 64 | AD16: 37
B17: Other expenses | C17: Other Expenses | E17: 4576 | F17: 4686 | G17: 4813 | I17: =F17-E17 -> 110 | J17: =F17/G17-1 -> -0.026386869 | L17: 4783 | M17: 5108 | N17: 7269 | P17: 5041 | Q17: 4717 | R17: 4807 | T17: 69197 | U17: 46497 | V17: 46557 | X17: 55225 | Y17: 5907 | Z17: 6488 | AB17: 6710 | AC17: 19498 | AD17: 41618
B18: Net loss from the disposal of assets | C18: Other Expenses | E18: 0 | F18: 1211 | G18: 4560 | I18: =F18-E18 -> 1211 | J18: =F18/G18-1 -> -0.73442982 | L18: 277 | M18: 883 | N18: 1304 | P18: 1685 | Q18: 1946 | R18: 2538 | T18: 0 | U18: 6568 | X18: -211 | Y18: 7307 | Z18: 25659 | AB18: 0 | AC18: 0 | AD18: 0 | AG18: Expense
B19: Net share of interests in joint ventures and associates using the equity method | C19: Other Expenses | E19: 0 | F19: 0 | G19: 0 | I19: =F19-E19 -> 0 | J19: =F19/G19-1 -> #DIV/0! | L19: 0 | M19: 1 | N19: 0 | P19: 0 | Q19: 0 | R19: 0 | T19: 0 | U19: 0 | AB19: 0 | AC19: 0 | AD19: 0
B20: Total expenses from continuing operations excluding depreciation, amortisation and impairment of non-financial Assets | C20: Total Expenses | E20: =SUM(E14:E19) -> 134879 | F20: =SUM(F14:F19) -> 136629 | G20: =SUM(G14:G19) -> 145642 | I20: =SUM(I14:I19) -> 1750 | J20: =F20/G20-1 -> -0.061884621 | L20: =SUM(L14:L19) -> 116430 | M20: =SUM(M14:M19) -> 108992 | N20: =SUM(N14:N19) -> 110364 | P20: =SUM(P14:P19) -> 111459 | Q20: =SUM(Q14:Q19) -> 113216 | R20: =SUM(R14:R19) -> 107265 | T20: =SUM(T14:T19) -> 603493 | U20: =SUM(U14:U19) -> 646072 | V20: =SUM(V14:V19) -> 622718 | X20: =SUM(X14:X19) -> 273782 | Y20: =SUM(Y14:Y19) -> 313493 | Z20: =SUM(Z14:Z19) -> 321737 | AB20: =SUM(AB14:AB19) -> 178855 | AC20: =SUM(AC14:AC19) -> 190825 | AD20: =SUM(AD14:AD19) -> 194868
B21: Operating result from continuing operations excluding depreciation, amortisation and impairment of non-financial assets | C21: Operating Result Excl Dep | E21: =E13-E20 -> 42606 | F21: =F13-F20 -> 88492 | G21: =G13-G20 -> -2890 | I21: =I13-I20 -> 45886 | J21: =F21/G21-1 -> -31.620069 | L21: =L13-L20 -> 25902 | M21: =M13-M20 -> 45588 | N21: =N13-N20 -> 41293 | P21: =P13-P20 -> 21072 | Q21: =Q13-Q20 -> 26376 | R21: =R13-R20 -> 29105 | T21: =T13-T20 -> 242190 | U21: =U13-U20 -> 263676 | V21: =V13-V20 -> 271859 | X21: =X13-X20 -> 148066 | Y21: =Y13-Y20 -> 125711 | Z21: =Z13-Z20 -> 150089 | AB21: =AB13-AB20 -> 145864 | AC21: =AC13-AC20 -> 226626 | AD21: =AD13-AD20 -> 188615
B22: Depreciation, amortisation and impairment of non-financial assets | C22: Depreciation | E22: 25461 | F22: 25979 | G22: 25107 | I22: =F22-E22 -> 518 | J22: =F22/G22-1 -> 0.03473135 | L22: 31095 | M22: 30411 | N22: 28240 | P22: 16947.5 | Q22: 16413 | R22: 15348 | T22: 126789 | U22: 130214 | V22: 123938 | X22: 66500 | Y22: 70059 | Z22: 61531 | AB22: 29613 | AC22: 30232 | AD22: 26904
B23: Operating result from continuing operations | C23: Operating Result from Operations | E23: =E21-E22 -> 17145 | F23: =F21-F22 -> 62513 | G23: =G21-G22 -> -27997 | I23: =I21-I22 -> 45368 | J23: =F23/G23-1 -> -3.2328464 | L23: =L21-L22 -> -5193 | M23: =M21-M22 -> 15177 | N23: =N21-N22 -> 13053 | P23: =P21-P22 -> 4124.5 | Q23: =Q21-Q22 -> 9963 | R23: =R21-R22 -> 13757 | T23: =T21-T22 -> 115401 | U23: =U21-U22 -> 133462 | V23: =V21-V22 -> 147921 | X23: =X21-X22 -> 81566 | Y23: =Y21-Y22 -> 55652 | Z23: =Z21-Z22 -> 88558 | AB23: =AB21-AB22 -> 116251 | AC23: =AC21-AC22 -> 196394 | AD23: =AD21-AD22 -> 161711
B24: Net operating result for the year attributable to Council | C24: Operating Result from Operations | E24: =E23 -> 17145 | F24: =F23 -> 62513 | G24: =G23 -> -27997 | I24: =I23 -> 45368 | J24: =F24/G24-1 -> -3.2328464 | L24: =L23 -> -5193 | M24: =M23 -> 15177 | N24: =N23 -> 13053 | P24: =P23 -> 4124.5 | Q24: =Q23 -> 9963 | R24: =R23 -> 13757 | T24: =T23 -> 115401 | U24: =U23 -> 133462 | V24: =V23 -> 147921 | X24: =X23 -> 81566 | Y24: =Y23 -> 55652 | Z24: =Z23 -> 88558 | AB24: =AB23 -> 116251 | AC24: =AC23 -> 196394 | AD24: =AD23 -> 161711
B25: Net operating result for the year before grants and contributions provided for capital purposes | C25: Operating Result from Operation before Govt Grants | E25: =E24-E8 -> 7205 | F25: =F24-F8 -> 20568 | G25: =G24-G8 -> -5794 | I25: =I24-I8 -> 13363 | J25: =F25/G25-1 -> -4.5498792 | L25: =L24-L8 -> -8251 | M25: =M24-M8 -> 1268 | N25: =N24-N8 -> -3637 | P25: =P24-P8 -> 1227.5 | Q25: =Q24-Q8 -> 1351 | R25: =R24-R8 -> -2455 | T25: =T24-T8 -> 20353 | U25: =U24-U8 -> 22131 | V25: =V24-V8 -> 30082 | X25: =X24-X8 -> 5834 | Y25: =Y24-Y8 -> -13546 | Z25: =Z24-Z8 -> 31106 | AB25: =AB24-AB8 -> 13847 | AC25: =AC24-AC8 -> 29210 | AD25: =AD24-AD8 -> 7089
B28: vs Budget
B29: YoY
B32: KPI
B33: Revenue | E33: =E13 -> 177485 | F33: =F13 -> 225121 | G33: =G13 -> 142752 | I33: =F33-E33 -> 47636 | J33: =F33/G33-1 -> 0.57700768 | L33: =L22/L12 -> #DIV/0! | M33: =M22/M12 -> #DIV/0! | N33: =N22/N12 -> #DIV/0! | P33: =P22/P12 -> #DIV/0! | Q33: =Q22/Q12 -> #DIV/0! | R33: =R22/R12 -> #DIV/0! | T33: =T22/T12 -> #DIV/0! | U33: =U22/U12 -> #DIV/0! | V33: =V22/V12 -> 7.1881452 | X33: =X22/X12 -> #DIV/0! | Y33: =Y22/Y12 -> #DIV/0! | Z33: =Z22/Z12 -> #DIV/0! | AB33: =AB22/AB12 -> 23.465135 | AC33: =AC22/AC12 -> 9.7459703 | AD33: =AD22/AD12 -> 11.177399
B34: NP % over Total Revenue | E34: =E23/E13 -> 0.096599713 | F34: =F23/F13 -> 0.27768622 | G34: =G23/G13 -> -0.19612335 | I34: =F34-E34 -> 0.18108651 | J34: =F34-G34 -> 0.47380957 | L34: =L23/L13 -> -0.036485119 | M34: =M23/M13 -> 0.098182171 | N34: =N23/N13 -> 0.086069222 | P34: =P23/P13 -> 0.031121021 | Q34: =Q23/Q13 -> 0.071372285 | R34: =R23/R13 -> 0.10087996 | T34: =T23/T13 -> 0.13645893 | U34: =U23/U13 -> 0.14670216 | V34: =V23/V13 -> 0.16535301 | X34: =X23/X13 -> 0.193354 | Y34: =Y23/Y13 -> 0.12671105 | Z34: =Z23/Z13 -> 0.18769207 | AB34: =AB23/AB13 -> 0.35800492 | AC34: =AC23/AC13 -> 0.47046001 | AD34: =AD23/AD13 -> 0.42169014
B35: NP before Govt Grant % over Total Revenue | E35: =E25/E13 -> 0.04059498 | F35: =F25/F13 -> 0.0913642 | G35: =G25/G13 -> -0.040587873 | I35: =F35-E35 -> 0.05076922 | J35: =F35-G35 -> 0.13195207 | L35: =L25/L13 -> -0.057970098 | M35: =M25/M13 -> 0.0082028723 | N35: =N25/N13 -> -0.023981748 | P35: =P25/P13 -> 0.009261984 | Q35: =Q25/Q13 -> 0.0096782051 | R35: =R25/R13 -> -0.018002493 | T35: =T25/T13 -> 0.024066938 | U35: =U25/U13 -> 0.024326517 | V35: =V25/V13 -> 0.033627066 | X35: =X25/X13 -> 0.013829626 | Y35: =Y25/Y13 -> -0.03084216 | Z35: =Z25/Z13 -> 0.065926846 | AB35: =AB25/AB13 -> 0.042643024 | AC35: =AC25/AC13 -> 0.069972284 | AD35: =AD25/AD13 -> 0.018485826
B36: Direct Result from Operations % over Direct Revenue | E36: =(SUM(E4:E5,E7,E8)-SUM(E14:E15))/SUM(E4:E5,E7:E8) -> 0.18158177 | F36: =(SUM(F4:F5,F7,F8)-SUM(F14:F15))/SUM(F4:F5,F7:F8) -> 0.33967345 | G36: =(SUM(G4:G5,G7,G8)-SUM(G14:G15))/SUM(G4:G5,G7:G8) -> -0.13691966 | I36: =F36-E36 -> 0.15809167 | J36: =F36-G36 -> 0.47659311 | L36: =(SUM(L4:L5,L7,L8)-SUM(L14:L15))/SUM(L4:L5,L7:L8) -> 0.11796316 | M36: =(SUM(M4:M5,M7,M8)-SUM(M14:M15))/SUM(M4:M5,M7:M8) -> 0.22188631 | N36: =(SUM(N4:N5,N7,N8)-SUM(N14:N15))/SUM(N4:N5,N7:N8) -> 0.2275332 | P36: =(SUM(P4:P5,P7,P8)-SUM(P14:P15))/SUM(P4:P5,P7:P8) -> -0.09085547 | Q36: =(SUM(Q4:Q5,Q7,Q8)-SUM(Q14:Q15))/SUM(Q4:Q5,Q7:Q8) -> -0.043197834 | R36: =(SUM(R4:R5,R7,R8)-SUM(R14:R15))/SUM(R4:R5,R7:R8) -> 0.052853102 | T36: =(SUM(T4:T5,T7,T8)-SUM(T14:T15))/SUM(T4:T5,T7:T8) -> 0.21537944 | U36: =(SUM(U4:U5,U7,U8)-SUM(U14:U15))/SUM(U4:U5,U7:U8) -> 0.16540989 | V36: =(SUM(V4:V5,V7,V8)-SUM(V14:V15))/SUM(V4:V5,V7:V8) -> 0.17141065 | X36: =(SUM(X4:X5,X7,X8)-SUM(X14:X15))/SUM(X4:X5,X7:X8) -> 0.42254369 | Y36: =(SUM(Y4:Y5,Y7,Y8)-SUM(Y14:Y15))/SUM(Y4:Y5,Y7:Y8) -> 0.17841672 | Z36: =(SUM(Z4:Z5,Z7,Z8)-SUM(Z14:Z15))/SUM(Z4:Z5,Z7:Z8) -> 0.14087149 | AB36: =(SUM(AB4:AB5,AB7,AB8)-SUM(AB14:AB15))/SUM(AB4:AB5,AB7:AB8) -> 0.41669293 | AC36: =(SUM(AC4:AC5,AC7,AC8)-SUM(AC14:AC15))/SUM(AC4:AC5,AC7:AC8) -> 0.53167548 | AD36: =(SUM(AD4:AD5,AD7,AD8)-SUM(AD14:AD15))/SUM(AD4:AD5,AD7:AD8) -> 0.54624529 | AF36: Revenue | AJ36: vs Budget | AK36: vs YoY
AF37: NP % over Total Revenue | AJ37: vs Budget | AK37: vs YoY
AF38: NP before Govt Grant % over Total Revenue
B39: Graph Data | AF39: Direct Result from Operations % over Direct Revenue
E40: =E3 -> Budget FY 25 | F40: =F3 -> Actual FY 25 | G40: =G3 -> Actual FY 24 | L40: =L3 -> Budget FY 25 | M40: =M3 -> Actual FY 25 | N40: =N3 -> Actual FY 24 | P40: =P3 -> Budget FY 25 | Q40: =Q3 -> Actual FY 25 | R40: =R3 -> Actual FY 24 | T40: =T3 -> Budget FY 25 | U40: =U3 -> Actual FY 25 | V40: =V3 -> Actual FY 24 | X40: =X3 -> Budget FY 25 | Y40: =Y3 -> Actual FY 25 | Z40: =Z3 -> Actual FY 24 | AB40: =AB3 -> Budget FY 25 | AC40: =AC3 -> Actual FY 25 | AD40: =AD3 -> Actual FY 24
B41: Operating Result | E41: =E23 -> 17145 | F41: =F23 -> 62513 | G41: =G23 -> -27997 | L41: =L23 -> -5193 | M41: =M23 -> 15177 | N41: =N23 -> 13053 | P41: =P23 -> 4124.5 | Q41: =Q23 -> 9963 | R41: =R23 -> 13757 | T41: =T23 -> 115401 | U41: =U23 -> 133462 | V41: =V23 -> 147921 | X41: =X23 -> 81566 | Y41: =Y23 -> 55652 | Z41: =Z23 -> 88558 | AB41: =AB23 -> 116251 | AC41: =AC23 -> 196394 | AD41: =AD23 -> 161711
B42: Total Expenses | E42: =SUM(E20,E22) -> 160340 | F42: =SUM(F20,F22) -> 162608 | G42: =SUM(G20,G22) -> 170749 | L42: =SUM(L20,L22) -> 147525 | M42: =SUM(M20,M22) -> 139403 | N42: =SUM(N20,N22) -> 138604 | P42: =SUM(P20,P22) -> 128406.5 | Q42: =SUM(Q20,Q22) -> 129629 | R42: =SUM(R20,R22) -> 122613 | T42: =SUM(T20,T22) -> 730282 | U42: =SUM(U20,U22) -> 776286 | V42: =SUM(V20,V22) -> 746656 | X42: =SUM(X20,X22) -> 340282 | Y42: =SUM(Y20,Y22) -> 383552 | Z42: =SUM(Z20,Z22) -> 383268 | AB42: =SUM(AB20,AB22) -> 208468 | AC42: =SUM(AC20,AC22) -> 221057 | AD42: =SUM(AD20,AD22) -> 221772
B43: NP % over Total Revenue | E43: =E34 -> 0.096599713 | F43: =F34 -> 0.27768622 | G43: =G34 -> -0.19612335 | L43: =L34 -> -0.036485119 | M43: =M34 -> 0.098182171 | N43: =N34 -> 0.086069222 | P43: =P34 -> 0.031121021 | Q43: =Q34 -> 0.071372285 | R43: =R34 -> 0.10087996 | T43: =T34 -> 0.13645893 | U43: =U34 -> 0.14670216 | V43: =V34 -> 0.16535301 | X43: =X34 -> 0.193354 | Y43: =Y34 -> 0.12671105 | Z43: =Z34 -> 0.18769207 | AB43: =AB34 -> 0.35800492 | AC43: =AC34 -> 0.47046001 | AD43: =AD34 -> 0.42169014
B44: NP before Govt Grant % over Total Revenue | E44: =E35 -> 0.04059498 | F44: =F35 -> 0.0913642 | G44: =G35 -> -0.040587873 | L44: =L35 -> -0.057970098 | M44: =M35 -> 0.0082028723 | N44: =N35 -> -0.023981748 | P44: =P35 -> 0.009261984 | Q44: =Q35 -> 0.0096782051 | R44: =R35 -> -0.018002493 | T44: =T35 -> 0.024066938 | U44: =U35 -> 0.024326517 | V44: =V35 -> 0.033627066 | X44: =X35 -> 0.013829626 | Y44: =Y35 -> -0.03084216 | Z44: =Z35 -> 0.065926846 | AB44: =AB35 -> 0.042643024 | AC44: =AC35 -> 0.069972284 | AD44: =AD35 -> 0.018485826
B45: Direct Result from Operations % over Direct Revenue | E45: =E36 -> 0.18158177 | F45: =F36 -> 0.33967345 | G45: =G36 -> -0.13691966 | L45: =L36 -> 0.11796316 | M45: =M36 -> 0.22188631 | N45: =N36 -> 0.2275332 | P45: =P36 -> -0.09085547 | Q45: =Q36 -> -0.043197834 | R45: =R36 -> 0.052853102 | T45: =T36 -> 0.21537944 | U45: =U36 -> 0.16540989 | V45: =V36 -> 0.17141065 | X45: =X36 -> 0.42254369 | Y45: =Y36 -> 0.17841672 | Z45: =Z36 -> 0.14087149 | AB45: =AB36 -> 0.41669293 | AC45: =AC36 -> 0.53167548 | AD45: =AD36 -> 0.54624529

Sheet City of Sydney
B3: Accounts | C3: Account Category | D3: Budget FY 25 | E3: Actual FY 25 | F3: Actual FY 24 | G3: vs Budget | H3: YoY
B4: Rates and annual charges | C4: Direct Income | D4: 419230 | E4: 420955 | F4: 397592 | G4: =E4-D4 -> 1725 | H4: =IF(F4=0,0,(E4/F4-1)) -> 0.058761243
B5: User charges and fees | C5: Direct Income | D5: 149206 | E5: 162346 | F5: 163152 | G5: =E5-D5 -> 13140 | H5: =IF(F5=0,0,(E5/F5-1)) -> -0.0049401785
B6: Other revenues | C6: Other Income | D6: 42362 | E6: 50103 | F6: 41915 | G6: =E6-D6 -> 7741 | H6: =IF(F6=0,0,(E6/F6-1)) -> 0.19534773
B7: Grants and contributions provided for operating purposes | C7: Direct Income | D7: 17477 | E7: 15652 | F7: 16508 | G7: =E7-D7 -> -1825 | H7: =IF(F7=0,0,(E7/F7-1)) -> -0.051853647
B8: Grants and contributions provided for capital purposes | C8: Direct Income | D8: 95048 | E8: 111331 | F8: 117839 | G8: =E8-D8 -> 16283 | H8: =IF(F8=0,0,(E8/F8-1)) -> -0.055227896
B9: Interest and investment income | C9: Other Income | D9: 34285 | E9: 39676 | F9: 39591 | G9: =E9-D9 -> 5391 | H9: =IF(F9=0,0,(E9/F9-1)) -> 0.0021469526
B10: Other income | C10: Other Income | D10: 88075 | E10: 109685 | F10: 100738 | G10: =E10-D10 -> 21610 | H10: =IF(F10=0,0,(E10/F10-1)) -> 0.088814549
B11: Fair Value increment / (Decrement) on Investment Properties | C11: Other Income | D11: 0 | E11: 0 | F11: 0 | G11: =E11-D11 -> 0 | H11: =IF(F11=0,0,(E11/F11-1)) -> 0
B12: Net Gain from disposal of Assets | C12: Other Income | D12: 0 | E12: 0 | F12: 17242 | H12: =IF(F12=0,0,(E12/F12-1)) -> -1
B13: Total income from continuing operations | C13: Total Income | D13: 845683 | E13: 909748 | F13: 894577 | G13: =SUM(G4:G12) -> 64065 | H13: =IF(F13=0,0,(E13/F13-1)) -> 0.016958853
B14: Employee benefits and on-costs | C14: Direct Expenses | D14: 289337 | E14: 306623 | F14: 276897 | G14: =E14-D14 -> 17286 | H14: =IF(F14=0,0,(E14/F14-1)) -> 0.107354
B15: Materials and services | C15: Direct Expenses | D15: 244959 | E15: 286173 | F15: 299048 | G15: =E15-D15 -> 41214 | H15: =IF(F15=0,0,(E15/F15-1)) -> -0.043053289
B16: Borrowing costs | C16: Other Expenses | D16: 0 | E16: 211 | F16: 216 | G16: =E16-D16 -> 211 | H16: =IF(F16=0,0,(E16/F16-1)) -> -0.023148148
B17: Other expenses | C17: Other Expenses | D17: 69197 | E17: 46497 | F17: 46557 | G17: =E17-D17 -> -22700 | H17: =IF(F17=0,0,(E17/F17-1)) -> -0.0012887428
B18: Net loss from the disposal of assets | C18: Other Expenses | D18: 0 | E18: 6568 | G18: =E18-D18 -> 6568 | H18: =IF(F18=0,0,(E18/F18-1)) -> 0
B19: Net share of interests in joint ventures and associates using the equity method | C19: Other Expenses | D19: 0 | E19: 0 | G19: =E19-D19 -> 0 | H19: =IF(F19=0,0,(E19/F19-1)) -> 0
B20: Total expenses from continuing operations excluding depreciation, amortisation and impairment of non-financial Assets | C20: Total Expenses | D20: 603493 | E20: 646072 | F20: 622718 | G20: =SUM(G14:G19) -> 42579 | H20: =IF(F20=0,0,(E20/F20-1)) -> 0.037503332
B21: Operating result from continuing operations excluding depreciation, amortisation and impairment of non-financial assets | C21: Operating Result Excl Dep | D21: 242190 | E21: 263676 | F21: 271859 | G21: =G13-G20 -> 21486 | H21: =IF(F21=0,0,(E21/F21-1)) -> -0.030100162
B22: Depreciation, amortisation and impairment of non-financial assets | C22: Depreciation | D22: 126789 | E22: 130214 | F22: 123938 | G22: =E22-D22 -> 3425 | H22: =IF(F22=0,0,(E22/F22-1)) -> 0.050638222
B23: Operating result from continuing operations | C23: Operating Result from Operations | D23: 115401 | E23: 133462 | F23: 147921 | G23: =G21-G22 -> 18061 | H23: =IF(F23=0,0,(E23/F23-1)) -> -0.097748122
B24: Net operating result for the year attributable to Council | C24: Operating Result from Operations | D24: 115401 | E24: 133462 | F24: 147921 | G24: =G23 -> 18061 | H24: =IF(F24=0,0,(E24/F24-1)) -> -0.097748122
B25: Net operating result for the year before grants and contributions provided for capital purposes | C25: Operating Result from Operation before Govt Grants | D25: 20353 | E25: 22131 | F25: 30082 | G25: =G24-G8 -> 1778 | H25: =IF(F25=0,0,(E25/F25-1)) -> -0.26431088
B27: KPI
B28: Revenue | D28: 845683 | E28: 909748 | F28: 894577 | G28: =SUM(G24:G27) -> 19839 | H28: =E28/F28-1 -> 0.016958853
B29: NP % over Total Revenue | D29: 0.13645893 | E29: 0.14670216 | F29: 0.16535301 | G29: =E29-D29 -> 0.01024323 | H29: =E29-F29 -> -0.018650847
B30: NP before Govt Grant % over Total Revenue | D30: 0.024066938 | E30: 0.024326517 | F30: 0.033627066 | G30: =E30-D30 -> 0.00025957918 | H30: =E30-F30 -> -0.0093005494
B31: Direct Result from Operations % over Direct Revenue | D31: 0.21537944 | E31: 0.16540989 | F31: 0.17141065 | G31: =E31-D31 -> -0.049969549 | H31: =E31-F31 -> -0.0060007574
B34: Graph Data
D35: =D3 -> Budget FY 25 | E35: =E3 -> Actual FY 25 | F35: =F3 -> Actual FY 24
B36: Operating Result | D36: =D23 -> 115401 | E36: =E23 -> 133462 | F36: =F23 -> 147921
B37: Total Expenses | D37: =SUM(D20,D22) -> 730282 | E37: =SUM(E20,E22) -> 776286 | F37: =SUM(F20,F22) -> 746656
B38: NP % over Total Revenue | D38: =D29 -> 0.13645893 | E38: =E29 -> 0.14670216 | F38: =F29 -> 0.16535301
B39: NP before Govt Grant % over Total Revenue | D39: =D30 -> 0.024066938 | E39: =E30 -> 0.024326517 | F39: =F30 -> 0.033627066
B40: Direct Result from Operations % over Direct Revenue | D40: =D31 -> 0.21537944 | E40: =E31 -> 0.16540989 | F40: =F31 -> 0.17141065
B41: Total Revenue | D41: =D37+D36 -> 845683 | E41: =E37+E36 -> 909748 | F41: =F37+F36 -> 894577

Sheet City of Parramatta
B3: Accounts | C3: Account Category | D3: Budget FY 25 | E3: Actual FY 25 | F3: Actual FY 24 | G3: vs Budget | H3: YoY
B4: Rates and annual charges | C4: Direct Income | D4: 229252 | E4: 231565 | F4: 221620 | G4: =E4-D4 -> 2313 | H4: =IF(F4=0,0,(E4/F4-1)) -> 0.044874109
B5: User charges and fees | C5: Direct Income | D5: 49973 | E5: 46819 | F5: 41788 | G5: =E5-D5 -> -3154 | H5: =IF(F5=0,0,(E5/F5-1)) -> 0.12039341
B6: Other revenues | C6: Other Income | D6: 18880 | E6: 18382 | F6: 12358 | G6: =E6-D6 -> -498 | H6: =IF(F6=0,0,(E6/F6-1)) -> 0.48745752
B7: Grants and contributions provided for operating purposes | C7: Direct Income | D7: 23721 | E7: 17849 | F7: 16057 | G7: =E7-D7 -> -5872 | H7: =IF(F7=0,0,(E7/F7-1)) -> 0.11160242
B8: Grants and contributions provided for capital purposes | C8: Direct Income | D8: 75732 | E8: 69198 | F8: 57452 | G8: =E8-D8 -> -6534 | H8: =IF(F8=0,0,(E8/F8-1)) -> 0.20444893
B9: Interest and investment income | C9: Other Income | D9: 23690 | E9: 28486 | F9: 30898 | G9: =E9-D9 -> 4796 | H9: =IF(F9=0,0,(E9/F9-1)) -> -0.078063305
B10: Other income | C10: Other Income | D10: 600 | E10: 26905 | F10: 91653 | G10: =E10-D10 -> 26305 | H10: =IF(F10=0,0,(E10/F10-1)) -> -0.70644714
B11: Fair Value increment / (Decrement) on Investment Properties | C11: Other Income | G11: =E11-D11 -> 0 | H11: =IF(F11=0,0,(E11/F11-1)) -> 0
B12: Net Gain from disposal of Assets | C12: Other Income | H12: =IF(F12=0,0,(E12/F12-1)) -> 0
B13: Total income from continuing operations | C13: Total Income | D13: =SUM(D4:D12) -> 421848 | E13: =SUM(E4:E12) -> 439204 | F13: =SUM(F4:F12) -> 471826 | G13: =SUM(G4:G12) -> 17356 | H13: =IF(F13=0,0,(E13/F13-1)) -> -0.069139895
B14: Employee benefits and on-costs | C14: Direct Expenses | D14: 145934 | E14: 164786 | F14: 159530 | G14: =E14-D14 -> 18852 | H14: =IF(F14=0,0,(E14/F14-1)) -> 0.032946781
B15: Materials and services | C15: Direct Expenses | D15: 72736 | E15: 135446 | F15: 129925 | G15: =E15-D15 -> 62710 | H15: =IF(F15=0,0,(E15/F15-1)) -> 0.042493746
B16: Borrowing costs | C16: Other Expenses | D16: 98 | E16: 47 | F16: 135 | G16: =E16-D16 -> -51 | H16: =IF(F16=0,0,(E16/F16-1)) -> -0.65185185
B17: Other expenses | C17: Other Expenses | D17: 55225 | E17: 5907 | F17: 6488 | G17: =E17-D17 -> -49318 | H17: =IF(F17=0,0,(E17/F17-1)) -> -0.089549938
B18: Net loss from the disposal of assets | C18: Other Expenses | D18: -211 | E18: 7307 | F18: 25659 | G18: =E18-D18 -> 7518 | H18: =IF(F18=0,0,(E18/F18-1)) -> -0.71522663
B19: Net share of interests in joint ventures and associates using the equity method | C19: Other Expenses | G19: =E19-D19 -> 0 | H19: =IF(F19=0,0,(E19/F19-1)) -> 0
B20: Total expenses from continuing operations excluding depreciation, amortisation and impairment of non-financial Assets | C20: Total Expenses | D20: =SUM(D14:D19) -> 273782 | E20: =SUM(E14:E19) -> 313493 | F20: =SUM(F14:F19) -> 321737 | G20: =SUM(G14:G19) -> 39711 | H20: =IF(F20=0,0,(E20/F20-1)) -> -0.025623413
B21: Operating result from continuing operations excluding depreciation, amortisation and impairment of non-financial assets | C21: Operating Result Excl Dep | D21: =D13-D20 -> 148066 | E21: =E13-E20 -> 125711 | F21: =F13-F20 -> 150089 | G21: =G13-G20 -> -22355 | H21: =IF(F21=0,0,(E21/F21-1)) -> -0.16242363
B22: Depreciation, amortisation and impairment of non-financial assets | C22: Depreciation | D22: 66500 | E22: 70059 | F22: 61531 | G22: =E22-D22 -> 3559 | H22: =IF(F22=0,0,(E22/F22-1)) -> 0.1385968
B23: Operating result from continuing operations | C23: Operating Result from Operations | D23: =D21-D22 -> 81566 | E23: =E21-E22 -> 55652 | F23: =F21-F22 -> 88558 | G23: =G21-G22 -> -25914 | H23: =IF(F23=0,0,(E23/F23-1)) -> -0.37157569
B24: Net operating result for the year attributable to Council | C24: Operating Result from Operations | D24: =D23 -> 81566 | E24: =E23 -> 55652 | F24: =F23 -> 88558 | G24: =G23 -> -25914 | H24: =IF(F24=0,0,(E24/F24-1)) -> -0.37157569
B25: Net operating result for the year before grants and contributions provided for capital purposes | C25: Operating Result from Operation before Govt Grants | D25: =D24-D8 -> 5834 | E25: =E24-E8 -> -13546 | F25: =F24-F8 -> 31106 | G25: =G24-G8 -> -19380 | H25: =IF(F25=0,0,(E25/F25-1)) -> -1.4354787
B27: KPI
B28: Revenue | D28: 324719 | E28: 417451 | F28: 383483 | G28: 90892 | H28: 0.09
B29: NP % over Total Revenue | D29: =D23/D13 -> 0.193354 | E29: =E23/E13 -> 0.12671105 | F29: =F23/F13 -> 0.18769207 | G29: =E29-D29 -> -0.066642954 | H29: =E29-F29 -> -0.060981023
B30: NP before Govt Grant % over Total Revenue | D30: =D25/D13 -> 0.013829626 | E30: =E25/E13 -> -0.03084216 | F30: =F25/F13 -> 0.065926846 | G30: =E30-D30 -> -0.044671786 | H30: =E30-F30 -> -0.096769006
B31: Direct Result from Operations % over Direct Revenue | D31: =(SUM(D4:D5,D7,D8)-SUM(D14:D15))/SUM(D4:D5,D7:D8) -> 0.42254369 | E31: =(SUM(E4:E5,E7,E8)-SUM(E14:E15))/SUM(E4:E5,E7:E8) -> 0.17841672 | F31: =(SUM(F4:F5,F7,F8)-SUM(F14:F15))/SUM(F4:F5,F7:F8) -> 0.14087149 | G31: =E31-D31 -> -0.24412697 | H31: =E31-F31 -> 0.037545228
B34: Graph Data
D35: =D3 -> Budget FY 25 | E35: =E3 -> Actual FY 25 | F35: =F3 -> Actual FY 24
B36: Operating Result | D36: =D23 -> 81566 | E36: =E23 -> 55652 | F36: =F23 -> 88558
B37: Total Expenses | D37: =SUM(D20,D22) -> 340282 | E37: =SUM(E20,E22) -> 383552 | F37: =SUM(F20,F22) -> 383268
B38: NP % over Total Revenue | D38: =D29 -> 0.193354 | E38: =E29 -> 0.12671105 | F38: =F29 -> 0.18769207
B39: NP before Govt Grant % over Total Revenue | D39: =D30 -> 0.013829626 | E39: =E30 -> -0.03084216 | F39: =F30 -> 0.065926846
B40: Direct Result from Operations % over Direct Revenue | D40: =D31 -> 0.42254369 | E40: =E31 -> 0.17841672 | F40: =F31 -> 0.14087149
B41: Total Revenue | D41: =D37+D36 -> 421848 | E41: =E37+E36 -> 439204 | F41: =F37+F36 -> 471826

Sheet Hill Shire Council
B3: Accounts | C3: Account Category | D3: Budget FY 25 | E3: Actual FY 25 | F3: Actual FY 24 | G3: vs Budget | H3: YoY
B4: Rates and annual charges | C4: Direct Income | D4: 142994 | E4: 144008 | F4: 128728 | G4: =E4-D4 -> 1014 | H4: =IF(F4=0,0,(E4/F4-1)) -> 0.11869989
B5: User charges and fees | C5: Direct Income | D5: 29911 | E5: 35509 | F5: 31193 | G5: =E5-D5 -> 5598 | H5: =IF(F5=0,0,(E5/F5-1)) -> 0.13836438
B6: Other revenues | C6: Other Income | D6: 6933 | E6: 9660 | F6: 9312 | G6: =E6-D6 -> 2727 | H6: =IF(F6=0,0,(E6/F6-1)) -> 0.037371134
B7: Grants and contributions provided for operating purposes | C7: Direct Income | D7: 19810 | E7: 18992 | F7: 23113 | G7: =E7-D7 -> -818 | H7: =IF(F7=0,0,(E7/F7-1)) -> -0.17829793
B8: Grants and contributions provided for capital purposes | C8: Direct Income | D8: 102404 | E8: 167184 | F8: 154622 | G8: =E8-D8 -> 64780 | H8: =IF(F8=0,0,(E8/F8-1)) -> 0.08124329
B9: Interest and investment income | C9: Other Income | D9: 12978 | E9: 30305 | F9: 25956 | G9: =E9-D9 -> 17327 | H9: =IF(F9=0,0,(E9/F9-1)) -> 0.16755278
B10: Other income | C10: Other Income | D10: 8427 | E10: 8691 | F10: 8152 | G10: =E10-D10 -> 264 | H10: =IF(F10=0,0,(E10/F10-1)) -> 0.066118744
B11: Fair Value increment / (Decrement) on Investment Properties | C11: Other Income | G11: =E11-D11 -> 0 | H11: =IF(F11=0,0,(E11/F11-1)) -> 0
B12: Net Gain from disposal of Assets | C12: Other Income | D12: 1262 | E12: 3102 | F12: 2407 | H12: =IF(F12=0,0,(E12/F12-1)) -> 0.28874117
B13: Total income from continuing operations | C13: Total Income | D13: 324719 | E13: 417451 | F13: 383483 | G13: =SUM(G4:G12) -> 90892 | H13: =IF(F13=0,0,(E13/F13-1)) -> 0.08857759
B14: Employee benefits and on-costs | C14: Direct Expenses | D14: 83698 | E14: 81713 | F14: 73247 | G14: =E14-D14 -> -1985 | H14: =IF(F14=0,0,(E14/F14-1)) -> 0.11558153
B15: Materials and services | C15: Direct Expenses | D15: 88447 | E15: 89550 | F15: 79966 | G15: =E15-D15 -> 1103 | H15: =IF(F15=0,0,(E15/F15-1)) -> 0.11985094
B16: Borrowing costs | C16: Other Expenses | D16: 0 | E16: 64 | F16: 37 | G16: =E16-D16 -> 64 | H16: =IF(F16=0,0,(E16/F16-1)) -> 0.72972973
B17: Other expenses | C17: Other Expenses | D17: 6710 | E17: 19498 | F17: 41618 | G17: =E17-D17 -> 12788 | H17: =IF(F17=0,0,(E17/F17-1)) -> -0.53150079
B18: Net loss from the disposal of assets | C18: Other Expenses | D18: 0 | E18: 0 | F18: 0 | G18: =E18-D18 -> 0 | H18: =IF(F18=0,0,(E18/F18-1)) -> 0
B19: Net share of interests in joint ventures and associates using the equity method | C19: Other Expenses | D19: 0 | E19: 0 | F19: 0 | G19: =E19-D19 -> 0 | H19: =IF(F19=0,0,(E19/F19-1)) -> 0
B20: Total expenses from continuing operations excluding depreciation, amortisation and impairment of non-financial Assets | C20: Total Expenses | D20: 178855 | E20: 190825 | F20: 194868 | G20: =SUM(G14:G19) -> 11970 | H20: =IF(F20=0,0,(E20/F20-1)) -> -0.020747378
B21: Operating result from continuing operations excluding depreciation, amortisation and impairment of non-financial assets | C21: Operating Result Excl Dep | D21: 145864 | E21: 226626 | F21: 188615 | G21: =G13-G20 -> 78922 | H21: =IF(F21=0,0,(E21/F21-1)) -> 0.20152692
B22: Depreciation, amortisation and impairment of non-financial assets | C22: Depreciation | D22: 29613 | E22: 30232 | F22: 26904 | G22: =E22-D22 -> 619 | H22: =IF(F22=0,0,(E22/F22-1)) -> 0.12369908
B23: Operating result from continuing operations | C23: Operating Result from Operations | D23: 116251 | E23: 196394 | F23: 161711 | G23: =G21-G22 -> 78303 | H23: =IF(F23=0,0,(E23/F23-1)) -> 0.21447521
B24: Net operating result for the year attributable to Council | C24: Operating Result from Operations | D24: 116251 | E24: 196394 | F24: 161711 | G24: =G23 -> 78303 | H24: =IF(F24=0,0,(E24/F24-1)) -> 0.21447521
B25: Net operating result for the year before grants and contributions provided for capital purposes | C25: Operating Result from Operation before Govt Grants | D25: 13847 | E25: 29210 | F25: 7089 | G25: =G24-G8 -> 13523 | H25: =IF(F25=0,0,(E25/F25-1)) -> 3.1204683
B27: KPI
B28: Revenue | D28: 324719 | E28: 417451 | F28: 383483 | G28: =SUM(G24:G27) -> 91826 | H28: =E28/F28-1 -> 0.08857759
B29: NP % over Total Revenue | D29: 0.35800492 | E29: 0.47046001 | F29: 0.42169014 | G29: =E29-D29 -> 0.11245508 | H29: =E29-F29 -> 0.048769866
B30: NP before Govt Grant % over Total Revenue | D30: 0.042643024 | E30: 0.069972284 | F30: 0.018485826 | G30: =E30-D30 -> 0.027329261 | H30: =E30-F30 -> 0.051486458
B31: Direct Result from Operations % over Direct Revenue | D31: 0.41669293 | E31: 0.53167548 | F31: 0.54624529 | G31: =E31-D31 -> 0.11498255 | H31: =E31-F31 -> -0.014569815
B34: Graph Data
D35: =D3 -> Budget FY 25 | E35: =E3 -> Actual FY 25 | F35: =F3 -> Actual FY 24
B36: Operating Result | D36: =D23 -> 116251 | E36: =E23 -> 196394 | F36: =F23 -> 161711
B37: Total Expenses | D37: =SUM(D20,D22) -> 208468 | E37: =SUM(E20,E22) -> 221057 | F37: =SUM(F20,F22) -> 221772
B38: NP % over Total Revenue | D38: =D29 -> 0.35800492 | E38: =E29 -> 0.47046001 | F38: =F29 -> 0.42169014
B39: NP before Govt Grant % over Total Revenue | D39: =D30 -> 0.042643024 | E39: =E30 -> 0.069972284 | F39: =F30 -> 0.018485826
B40: Direct Result from Operations % over Direct Revenue | D40: =D31 -> 0.41669293 | E40: =E31 -> 0.53167548 | F40: =F31 -> 0.54624529
B41: Total Revenue | D41: =D37+D36 -> 324719 | E41: =E37+E36 -> 417451 | F41: =F37+F36 -> 383483

Sheet Hornsby Council
B3: Accounts | C3: Account Category | D3: Budget FY 25 | E3: Actual FY 25 | F3: Actual FY 24 | G3: vs Budget | H3: YoY
B4: Rates and annual charges | C4: Direct Income | D4: 125129 | E4: 126012 | F4: 116643 | G4: =E4-D4 -> 883 | H4: =IF(F4=0,0,(E4/F4-1)) -> 0.080322008
B5: User charges and fees | C5: Direct Income | D5: 14958 | E5: 16427 | F5: 14762 | G5: =E5-D5 -> 1469 | H5: =IF(F5=0,0,(E5/F5-1)) -> 0.11278959
B6: Other revenues | C6: Other Income | D6: 3963 | E6: 4636 | F6: 4179 | G6: =E6-D6 -> 673 | H6: =IF(F6=0,0,(E6/F6-1)) -> 0.10935631
B7: Grants and contributions provided for operating purposes | C7: Direct Income | D7: 9174 | E7: 13562 | F7: 10642 | G7: =E7-D7 -> 4388 | H7: =IF(F7=0,0,(E7/F7-1)) -> 0.27438451
B8: Grants and contributions provided for capital purposes | C8: Direct Income | D8: 9940 | E8: 41945 | F8: -22203 | G8: =E8-D8 -> 32005 | H8: =IF(F8=0,0,(E8/F8-1)) -> -2.8891591
B9: Interest and investment income | C9: Other Income | D9: 10271 | E9: 12548 | F9: 12970 | G9: =E9-D9 -> 2277 | H9: =IF(F9=0,0,(E9/F9-1)) -> -0.032536623
B10: Other income | C10: Other Income | D10: 4050 | E10: 9991 | F10: 5759 | G10: =E10-D10 -> 5941 | H10: =IF(F10=0,0,(E10/F10-1)) -> 0.7348498
B11: Fair Value increment / (Decrement) on Investment Properties | C11: Other Income | D11: 0 | E11: 0 | F11: 0 | G11: =E11-D11 -> 0 | H11: =IF(F11=0,0,(E11/F11-1)) -> 0
B12: Net Gain from disposal of Assets | C12: Other Income | H12: =IF(F12=0,0,(E12/F12-1)) -> 0
B13: Total income from continuing operations | C13: Total Income | D13: =SUM(D4:D12) -> 177485 | E13: =SUM(E4:E12) -> 225121 | F13: =SUM(F4:F12) -> 142752 | G13: =SUM(G4:G12) -> 47636 | H13: =IF(F13=0,0,(E13/F13-1)) -> 0.57700768
B14: Employee benefits and on-costs | C14: Direct Expenses | D14: 58497 | E14: 58441 | F14: 54031 | G14: =E14-D14 -> -56 | H14: =IF(F14=0,0,(E14/F14-1)) -> 0.081619811
B15: Materials and services | C15: Direct Expenses | D15: 71796 | E15: 72268 | F15: 82222 | G15: =E15-D15 -> 472 | H15: =IF(F15=0,0,(E15/F15-1)) -> -0.12106249
B16: Borrowing costs | C16: Other Expenses | D16: 10 | E16: 23 | F16: 16 | G16: =E16-D16 -> 13 | H16: =IF(F16=0,0,(E16/F16-1)) -> 0.4375
B17: Other expenses | C17: Other Expenses | D17: 4576 | E17: 4686 | F17: 4813 | G17: =E17-D17 -> 110 | H17: =IF(F17=0,0,(E17/F17-1)) -> -0.026386869
B18: Net loss from the disposal of assets | C18: Other Expenses | D18: 0 | E18: 1211 | F18: 4560 | G18: =E18-D18 -> 1211 | H18: =IF(F18=0,0,(E18/F18-1)) -> -0.73442982
B19: Net share of interests in joint ventures and associates using the equity method | C19: Other Expenses | D19: 0 | E19: 0 | F19: 0 | G19: =E19-D19 -> 0 | H19: =IF(F19=0,0,(E19/F19-1)) -> 0
B20: Total expenses from continuing operations excluding depreciation, amortisation and impairment of non-financial Assets | C20: Total Expenses | D20: =SUM(D14:D19) -> 134879 | E20: =SUM(E14:E19) -> 136629 | F20: =SUM(F14:F19) -> 145642 | G20: =SUM(G14:G19) -> 1750 | H20: =IF(F20=0,0,(E20/F20-1)) -> -0.061884621
B21: Operating result from continuing operations excluding depreciation, amortisation and impairment of non-financial assets | C21: Operating Result Excl Dep | D21: =D13-D20 -> 42606 | E21: =E13-E20 -> 88492 | F21: =F13-F20 -> -2890 | G21: =G13-G20 -> 45886 | H21: =IF(F21=0,0,(E21/F21-1)) -> -31.620069
B22: Depreciation, amortisation and impairment of non-financial assets | C22: Depreciation | D22: 25461 | E22: 25979 | F22: 25107 | G22: =E22-D22 -> 518 | H22: =IF(F22=0,0,(E22/F22-1)) -> 0.03473135
B23: Operating result from continuing operations | C23: Operating Result from Operations | D23: =D21-D22 -> 17145 | E23: =E21-E22 -> 62513 | F23: =F21-F22 -> -27997 | G23: =G21-G22 -> 45368 | H23: =IF(F23=0,0,(E23/F23-1)) -> -3.2328464
B24: Net operating result for the year attributable to Council | C24: Operating Result from Operations | D24: =D23 -> 17145 | E24: =E23 -> 62513 | F24: =F23 -> -27997 | G24: =G23 -> 45368 | H24: =IF(F24=0,0,(E24/F24-1)) -> -3.2328464
B25: Net operating result for the year before grants and contributions provided for capital purposes | C25: Operating Result from Operation before Govt Grants | D25: =D24-D8 -> 7205 | E25: =E24-E8 -> 20568 | F25: =F24-F8 -> -5794 | G25: =G24-G8 -> 13363 | H25: =IF(F25=0,0,(E25/F25-1)) -> -4.5498792
B27: KPI
B28: Revenue | D28: =D13 -> 177485 | E28: =E13 -> 225121 | F28: =F13 -> 142752 | G28: =E28-D28 -> 47636 | H28: =E28/F28-1 -> 0.57700768
B29: NP % over Total Revenue | D29: =D23/D13 -> 0.096599713 | E29: =E23/E13 -> 0.27768622 | F29: =F23/F13 -> -0.19612335 | G29: =E29-D29 -> 0.18108651 | H29: =E29-F29 -> 0.47380957
B30: NP before Govt Grant % over Total Revenue | D30: =D25/D13 -> 0.04059498 | E30: =E25/E13 -> 0.0913642 | F30: =F25/F13 -> -0.040587873 | G30: =E30-D30 -> 0.05076922 | H30: =E30-F30 -> 0.13195207
B31: Direct Result from Operations % over Direct Revenue | D31: =(SUM(D4:D5,D7,D8)-SUM(D14:D15))/SUM(D4:D5,D7:D8) -> 0.18158177 | E31: =(SUM(E4:E5,E7,E8)-SUM(E14:E15))/SUM(E4:E5,E7:E8) -> 0.33967345 | F31: =(SUM(F4:F5,F7,F8)-SUM(F14:F15))/SUM(F4:F5,F7:F8) -> -0.13691966 | G31: =E31-D31 -> 0.15809167 | H31: =E31-F31 -> 0.47659311
B34: Graph Data
D35: =D3 -> Budget FY 25 | E35: =E3 -> Actual FY 25 | F35: =F3 -> Actual FY 24
B36: Operating Result | D36: =D23 -> 17145 | E36: =E23 -> 62513 | F36: =F23 -> -27997
B37: Total Expenses | D37: =SUM(D20,D22) -> 160340 | E37: =SUM(E20,E22) -> 162608 | F37: =SUM(F20,F22) -> 170749
B38: NP % over Total Revenue | D38: =D29 -> 0.096599713 | E38: =E29 -> 0.27768622 | F38: =F29 -> -0.19612335
B39: NP before Govt Grant % over Total Revenue | D39: =D30 -> 0.04059498 | E39: =E30 -> 0.0913642 | F39: =F30 -> -0.040587873
B40: Direct Result from Operations % over Direct Revenue | D40: =D31 -> 0.18158177 | E40: =E31 -> 0.33967345 | F40: =F31 -> -0.13691966
B41: Total Revenue | D41: =D37+D36 -> 177485 | E41: =E37+E36 -> 225121 | F41: =F37+F36 -> 142752

Sheet North Sydney Council
B3: Accounts | C3: Account Category | D3: Budget FY 25 | E3: Actual FY 25 | F3: Actual FY 24 | G3: vs Budget | H3: YoY
B4: Rates and annual charges | C4: Direct Income | D4: 79066 | E4: 79820 | F4: 75559 | G4: =E4-D4 -> 754 | H4: =IF(F4=0,0,(E4/F4-1)) -> 0.056393017
B5: User charges and fees | C5: Direct Income | D5: 36774 | E5: 30734 | F5: 32134 | G5: =E5-D5 -> -6040 | H5: =IF(F5=0,0,(E5/F5-1)) -> -0.043567561
B6: Other revenues | C6: Other Income | D6: 10216 | E6: 13967 | F6: 10239 | G6: =E6-D6 -> 3751 | H6: =IF(F6=0,0,(E6/F6-1)) -> 0.36409806
B7: Grants and contributions provided for operating purposes | C7: Direct Income | D7: 4666 | E7: 4869 | F7: 5453 | G7: =E7-D7 -> 203 | H7: =IF(F7=0,0,(E7/F7-1)) -> -0.10709701
B8: Grants and contributions provided for capital purposes | C8: Direct Income | D8: 3058 | E8: 13909 | F8: 16690 | G8: =E8-D8 -> 10851 | H8: =IF(F8=0,0,(E8/F8-1)) -> -0.16662672
B9: Interest and investment income | C9: Other Income | D9: 2665 | E9: 5759 | F9: 5612 | G9: =E9-D9 -> 3094 | H9: =IF(F9=0,0,(E9/F9-1)) -> 0.02619387
B10: Other income | C10: Other Income | D10: 5887 | E10: 5522 | F10: 5970 | G10: =E10-D10 -> -365 | H10: =IF(F10=0,0,(E10/F10-1)) -> -0.075041876
B11: Fair Value increment / (Decrement) on Investment Properties | C11: Other Income | D11: 0 | E11: 0 | F11: 0 | G11: =E11-D11 -> 0 | H11: =IF(F11=0,0,(E11/F11-1)) -> 0
B12: Net Gain from disposal of Assets | C12: Other Income | H12: =IF(F12=0,0,(E12/F12-1)) -> 0
B13: Total income from continuing operations | C13: Total Income | D13: 142332 | E13: 154580 | F13: 151657 | G13: =SUM(G4:G12) -> 12248 | H13: =IF(F13=0,0,(E13/F13-1)) -> 0.019273756
B14: Employee benefits and on-costs | C14: Direct Expenses | D14: 55651 | E14: 48080 | F14: 49118 | G14: =E14-D14 -> -7571 | H14: =IF(F14=0,0,(E14/F14-1)) -> -0.021132782
B15: Materials and services | C15: Direct Expenses | D15: 53337 | E15: 52555 | F15: 51176 | G15: =E15-D15 -> -782 | H15: =IF(F15=0,0,(E15/F15-1)) -> 0.026946225
B16: Borrowing costs | C16: Other Expenses | D16: 2382 | E16: 2365 | F16: 1497 | G16: =E16-D16 -> -17 | H16: =IF(F16=0,0,(E16/F16-1)) -> 0.57982632
B17: Other expenses | C17: Other Expenses | D17: 4783 | E17: 5108 | F17: 7269 | G17: =E17-D17 -> 325 | H17: =IF(F17=0,0,(E17/F17-1)) -> -0.29728986
B18: Net loss from the disposal of assets | C18: Other Expenses | D18: 277 | E18: 883 | F18: 1304 | G18: =E18-D18 -> 606 | H18: =IF(F18=0,0,(E18/F18-1)) -> -0.32285276
B19: Net share of interests in joint ventures and associates using the equity method | C19: Other Expenses | D19: 0 | E19: 1 | F19: 0 | G19: =E19-D19 -> 1 | H19: =IF(F19=0,0,(E19/F19-1)) -> 0
B20: Total expenses from continuing operations excluding depreciation, amortisation and impairment of non-financial Assets | C20: Total Expenses | D20: 116430 | E20: 108992 | F20: 110364 | G20: =SUM(G14:G19) -> -7438 | H20: =IF(F20=0,0,(E20/F20-1)) -> -0.01243159
B21: Operating result from continuing operations excluding depreciation, amortisation and impairment of non-financial assets | C21: Operating Result Excl Dep | D21: 25902 | E21: 45588 | F21: 41293 | G21: =G13-G20 -> 19686 | H21: =IF(F21=0,0,(E21/F21-1)) -> 0.10401279
B22: Depreciation, amortisation and impairment of non-financial assets | C22: Depreciation | D22: 31095 | E22: 30411 | F22: 28240 | G22: =E22-D22 -> -684 | H22: =IF(F22=0,0,(E22/F22-1)) -> 0.076876771
B23: Operating result from continuing operations | C23: Operating Result from Operations | D23: -5193 | E23: 15177 | F23: 13053 | G23: =G21-G22 -> 20370 | H23: =IF(F23=0,0,(E23/F23-1)) -> 0.16272121
B24: Net operating result for the year attributable to Council | C24: Operating Result from Operations | D24: -5193 | E24: 15177 | F24: 13053 | G24: =G23 -> 20370 | H24: =IF(F24=0,0,(E24/F24-1)) -> 0.16272121
B25: Net operating result for the year before grants and contributions provided for capital purposes | C25: Operating Result from Operation before Govt Grants | D25: -8251 | E25: 1268 | F25: -3637 | G25: =G24-G8 -> 9519 | H25: =IF(F25=0,0,(E25/F25-1)) -> -1.348639
B27: KPI
B28: Revenue | D28: 142332 | E28: 154580 | F28: 151657 | G28: =SUM(G24:G27) -> 29889 | H28: =E28/F28-1 -> 0.019273756
B29: NP % over Total Revenue | D29: -0.036485119 | E29: 0.098182171 | F29: 0.086069222 | G29: =E29-D29 -> 0.13466729 | H29: =E29-F29 -> 0.012112949
B30: NP before Govt Grant % over Total Revenue | D30: -0.057970098 | E30: 0.0082028723 | F30: -0.023981748 | G30: =E30-D30 -> 0.06617297 | H30: =E30-F30 -> 0.032184621
B31: Direct Result from Operations % over Direct Revenue | D31: 0.11796316 | E31: 0.22188631 | F31: 0.2275332 | G31: =E31-D31 -> 0.10392315 | H31: =E31-F31 -> -0.0056468876
B34: Graph Data
D35: =D3 -> Budget FY 25 | E35: =E3 -> Actual FY 25 | F35: =F3 -> Actual FY 24
B36: Operating Result | D36: =D23 -> -5193 | E36: =E23 -> 15177 | F36: =F23 -> 13053
B37: Total Expenses | D37: =SUM(D20,D22) -> 147525 | E37: =SUM(E20,E22) -> 139403 | F37: =SUM(F20,F22) -> 138604
B38: NP % over Total Revenue | D38: =D29 -> -0.036485119 | E38: =E29 -> 0.098182171 | F38: =F29 -> 0.086069222
B39: NP before Govt Grant % over Total Revenue | D39: =D30 -> -0.057970098 | E39: =E30 -> 0.0082028723 | F39: =F30 -> -0.023981748
B40: Direct Result from Operations % over Direct Revenue | D40: =D31 -> 0.11796316 | E40: =E31 -> 0.22188631 | F40: =F31 -> 0.2275332
B41: Total Revenue | D41: =D37+D36 -> 142332 | E41: =E37+E36 -> 154580 | F41: =F37+F36 -> 151657

Sheet Woollahra Council
B3: Accounts | C3: Account Category | D3: Budget FY 25 | E3: Actual FY 25 | F3: Actual FY 24 | G3: vs Budget | H3: YoY
B4: Rates and annual charges | C4: Direct Income | D4: 70681 | E4: 70552 | F4: 66136 | G4: =E4-D4 -> -129 | H4: =IF(F4=0,0,(E4/F4-1)) -> 0.066771501
B5: User charges and fees | C5: Direct Income | D5: 14655 | E5: 16689 | F5: 15565 | G5: =E5-D5 -> 2034 | H5: =IF(F5=0,0,(E5/F5-1)) -> 0.072213299
B6: Other revenues | C6: Other Income | D6: 16941 | E6: 15347 | F6: 16230 | G6: =E6-D6 -> -1594 | H6: =IF(F6=0,0,(E6/F6-1)) -> -0.054405422
B7: Grants and contributions provided for operating purposes | C7: Direct Income | D7: 5014 | E7: 4615 | F7: 5676 | G7: =E7-D7 -> -399 | H7: =IF(F7=0,0,(E7/F7-1)) -> -0.18692741
B8: Grants and contributions provided for capital purposes | C8: Direct Income | D8: 2897 | E8: 8612 | F8: 16212 | G8: =E8-D8 -> 5715 | H8: =IF(F8=0,0,(E8/F8-1)) -> -0.46878855
B9: Interest and investment income | C9: Other Income | D9: 3223 | E9: 6103 | F9: 5626 | G9: =E9-D9 -> 2880 | H9: =IF(F9=0,0,(E9/F9-1)) -> 0.084784927
B10: Other income | C10: Other Income | D10: 17920 | E10: 17655 | F10: 17608 | G10: =E10-D10 -> -265 | H10: =IF(F10=0,0,(E10/F10-1)) -> 0.0026692413
B11: Fair Value increment / (Decrement) on Investment Properties | C11: Other Income | D11: 1200 | E11: 19 | F11: -6683 | G11: =E11-D11 -> -1181 | H11: =IF(F11=0,0,(E11/F11-1)) -> -1.002843
B12: Net Gain from disposal of Assets | C12: Other Income | H12: =IF(F12=0,0,(E12/F12-1)) -> 0
B13: Total income from continuing operations | C13: Total Income | D13: 132531 | E13: 139592 | F13: 136370 | G13: =SUM(G4:G12) -> 7061 | H13: =IF(F13=0,0,(E13/F13-1)) -> 0.023626897
B14: Employee benefits and on-costs | C14: Direct Expenses | D14: 53223 | E14: 52968 | F14: 47706 | G14: =E14-D14 -> -255 | H14: =IF(F14=0,0,(E14/F14-1)) -> 0.11030059
B15: Materials and services | C15: Direct Expenses | D15: 48496 | E15: 51840 | F15: 50408 | G15: =E15-D15 -> 3344 | H15: =IF(F15=0,0,(E15/F15-1)) -> 0.028408189
B16: Borrowing costs | C16: Other Expenses | D16: 3014 | E16: 1745 | F16: 1806 | G16: =E16-D16 -> -1269 | H16: =IF(F16=0,0,(E16/F16-1)) -> -0.033776301
B17: Other expenses | C17: Other Expenses | D17: 5041 | E17: 4717 | F17: 4807 | G17: =E17-D17 -> -324 | H17: =IF(F17=0,0,(E17/F17-1)) -> -0.018722696
B18: Net loss from the disposal of assets | C18: Other Expenses | D18: 1685 | E18: 1946 | F18: 2538 | G18: =E18-D18 -> 261 | H18: =IF(F18=0,0,(E18/F18-1)) -> -0.23325453
B19: Net share of interests in joint ventures and associates using the equity method | C19: Other Expenses | D19: 0 | E19: 0 | F19: 0 | G19: =E19-D19 -> 0 | H19: =IF(F19=0,0,(E19/F19-1)) -> 0
B20: Total expenses from continuing operations excluding depreciation, amortisation and impairment of non-financial Assets | C20: Total Expenses | D20: 111459 | E20: 113216 | F20: 107265 | G20: =SUM(G14:G19) -> 1757 | H20: =IF(F20=0,0,(E20/F20-1)) -> 0.05547942
B21: Operating result from continuing operations excluding depreciation, amortisation and impairment of non-financial assets | C21: Operating Result Excl Dep | D21: 21072 | E21: 26376 | F21: 29105 | G21: =G13-G20 -> 5304 | H21: =IF(F21=0,0,(E21/F21-1)) -> -0.093763958
B22: Depreciation, amortisation and impairment of non-financial assets | C22: Depreciation | D22: 16947.5 | E22: 16413 | F22: 15348 | G22: =E22-D22 -> -534.5 | H22: =IF(F22=0,0,(E22/F22-1)) -> 0.069390149
B23: Operating result from continuing operations | C23: Operating Result from Operations | D23: 4124.5 | E23: 9963 | F23: 13757 | G23: =G21-G22 -> 5838.5 | H23: =IF(F23=0,0,(E23/F23-1)) -> -0.27578687
B24: Net operating result for the year attributable to Council | C24: Operating Result from Operations | D24: 4124.5 | E24: 9963 | F24: 13757 | G24: =G23 -> 5838.5 | H24: =IF(F24=0,0,(E24/F24-1)) -> -0.27578687
B25: Net operating result for the year before grants and contributions provided for capital purposes | C25: Operating Result from Operation before Govt Grants | D25: 1227.5 | E25: 1351 | F25: -2455 | G25: =G24-G8 -> 123.5 | H25: =IF(F25=0,0,(E25/F25-1)) -> -1.5503055
B27: KPI
B28: Revenue | D28: 132531 | E28: 139592 | F28: 136370 | G28: =SUM(G24:G27) -> 5962 | H28: =E28/F28-1 -> 0.023626897
B29: NP % over Total Revenue | D29: 0.031121021 | E29: 0.071372285 | F29: 0.10087996 | G29: =E29-D29 -> 0.040251264 | H29: =E29-F29 -> -0.029507674
B30: NP before Govt Grant % over Total Revenue | D30: 0.009261984 | E30: 0.0096782051 | F30: -0.018002493 | G30: =E30-D30 -> 0.00041622107 | H30: =E30-F30 -> 0.027680698
B31: Direct Result from Operations % over Direct Revenue | D31: -0.09085547 | E31: -0.043197834 | F31: 0.052853102 | G31: =E31-D31 -> 0.047657636 | H31: =E31-F31 -> -0.096050936
B34: Graph Data
D35: =D3 -> Budget FY 25 | E35: =E3 -> Actual FY 25 | F35: =F3 -> Actual FY 24
B36: Operating Result | D36: =D23 -> 4124.5 | E36: =E23 -> 9963 | F36: =F23 -> 13757
B37: Total Expenses | D37: =SUM(D20,D22) -> 128406.5 | E37: =SUM(E20,E22) -> 129629 | F37: =SUM(F20,F22) -> 122613
B38: NP % over Total Revenue | D38: =D29 -> 0.031121021 | E38: =E29 -> 0.071372285 | F38: =F29 -> 0.10087996
B39: NP before Govt Grant % over Total Revenue | D39: =D30 -> 0.009261984 | E39: =E30 -> 0.0096782051 | F39: =F30 -> -0.018002493
B40: Direct Result from Operations % over Direct Revenue | D40: =D31 -> -0.09085547 | E40: =E31 -> -0.043197834 | F40: =F31 -> 0.052853102
B41: Total Revenue | D41: =D37+D36 -> 132531 | E41: =E37+E36 -> 139592 | F41: =F37+F36 -> 136370

Sheet Comparitive data (KPIs)
A1: Actual 2025
B2: NP % over Total Revenue | C2: NP before Govt Grant % over Total Revenue | D2: Direct Result from Operations % over Direct Revenue | E2: Revenue (000) | F2: Operating Result (000)
A3: City of Sydney | B3: ='City of Sydney'!$E$29 -> 0.14670216 | C3: ='City of Sydney'!$E$30 -> 0.024326517 | D3: ='City of Sydney'!$E$31 -> 0.16540989 | E3: ='City of Sydney'!$E$13 -> 909748 | F3: ='City of Sydney'!$E$23 -> 133462
A4: City of Parramatta | B4: ='City of Parramatta'!$E$29 -> 0.12671105 | C4: ='City of Parramatta'!$E$30 -> -0.03084216 | D4: ='City of Parramatta'!$E$31 -> 0.17841672 | E4: ='City of Parramatta'!$E$13 -> 439204 | F4: ='City of Parramatta'!$E$23 -> 55652
A5: Hill Shire Council | B5: ='Hill Shire Council'!$E$29 -> 0.47046001 | C5: ='Hill Shire Council'!$E$30 -> 0.069972284 | D5: ='Hill Shire Council'!$E$31 -> 0.53167548 | E5: ='Hill Shire Council'!$E$13 -> 417451 | F5: ='Hill Shire Council'!$E$22 -> 30232
A6: Hornsby Council | B6: ='Hornsby Council'!$E$29 -> 0.27768622 | C6: ='Hornsby Council'!$E$30 -> 0.0913642 | D6: ='Hornsby Council'!$E$31 -> 0.33967345 | E6: ='Hornsby Council'!$E$13 -> 225121 | F6: ='Hornsby Council'!$E$23 -> 62513
A7: North Sydney Council | B7: ='North Sydney Council'!$E$29 -> 0.098182171 | C7: ='North Sydney Council'!$E$30 -> 0.0082028723 | D7: ='North Sydney Council'!$E$31 -> 0.22188631 | E7: ='North Sydney Council'!$E$13 -> 154580 | F7: ='North Sydney Council'!$E$23 -> 15177
A8: Woollahra Council | B8: ='Woollahra Council'!$E$29 -> 0.071372285 | C8: ='Woollahra Council'!$E$30 -> 0.0096782051 | D8: ='Woollahra Council'!$E$31 -> -0.043197834 | E8: ='Woollahra Council'!$E$13 -> 139592 | F8: ='Woollahra Council'!$E$23 -> 9963
A10: Actual 2024
B11: NP % over Total Revenue | C11: NP before Govt Grant % over Total Revenue | D11: Direct Result from Operations % over Direct Revenue | E11: Revenue (000) | F11: Operating Result (000)
A12: City of Sydney | B12: ='City of Sydney'!$F$29 -> 0.16535301 | C12: ='City of Sydney'!$F$30 -> 0.033627066 | D12: ='City of Sydney'!$F$31 -> 0.17141065 | E12: ='City of Sydney'!$F$13 -> 894577 | F12: ='City of Sydney'!$F$23 -> 147921
A13: City of Parramatta | B13: ='City of Parramatta'!$F$29 -> 0.18769207 | C13: ='City of Parramatta'!$F$30 -> 0.065926846 | D13: ='City of Parramatta'!$F$31 -> 0.14087149 | E13: ='City of Parramatta'!$F$13 -> 471826 | F13: ='City of Parramatta'!$F$23 -> 88558
A14: Hill Shire Council | B14: ='Hill Shire Council'!$F$29 -> 0.42169014 | C14: ='Hill Shire Council'!$F$30 -> 0.018485826 | D14: ='Hill Shire Council'!$F$31 -> 0.54624529 | E14: ='Hill Shire Council'!$F$13 -> 383483 | F14: ='Hill Shire Council'!$F$22 -> 26904
A15: Hornsby Council | B15: ='Hornsby Council'!$F$29 -> -0.19612335 | C15: ='Hornsby Council'!$F$30 -> -0.040587873 | D15: ='Hornsby Council'!$F$31 -> -0.13691966 | E15: ='Hornsby Council'!$F$13 -> 142752 | F15: ='Hornsby Council'!$F$23 -> -27997
A16: North Sydney Council | B16: ='North Sydney Council'!$F$29 -> 0.086069222 | C16: ='North Sydney Council'!$F$30 -> -0.023981748 | D16: ='North Sydney Council'!$F$31 -> 0.2275332 | E16: ='North Sydney Council'!$F$13 -> 151657 | F16: ='North Sydney Council'!$F$23 -> 13053
A17: Woollahra Council | B17: ='Woollahra Council'!$F$29 -> 0.10087996 | C17: ='Woollahra Council'!$F$30 -> -0.018002493 | D17: ='Woollahra Council'!$F$31 -> 0.052853102 | E17: ='Woollahra Council'!$F$13 -> 136370 | F17: ='Woollahra Council'!$F$23 -> 13757
